regressio/__init__.py
regressio/datagen.py
regressio/models.py
tests/__init__.py
tests/test_main.py
regressio-1.0.1.dist-info/METADATA
regressio-1.0.1.dist-info/WHEEL
regressio-1.0.1.dist-info/top_level.txt
regressio-1.0.1.dist-info/RECORD
