Metadata-Version: 2.1
Name: regressio
Version: 1.0.1
Summary: A python module for regression, interpolation and smoothing.
Home-page: https://github.com/brendanartley/regressio
Author: Brendan Artley
Author-email: brendanartley@gmail.com
License: MIT
Platform: UNKNOWN
Requires-Python: >=3.8
Requires-Dist: numpy
Requires-Dist: matplotlib
